poi_kml/__init__.py
poi_kml/fake_poi_list_generator.py
poi_kml/poi.py
poi_kml-0.1.2.dist-info/LICENSE
poi_kml-0.1.2.dist-info/WHEEL
poi_kml-0.1.2.dist-info/METADATA
poi_kml-0.1.2.dist-info/RECORD
