Metadata-Version: 2.1
Name: poi-kml
Version: 0.1.2
Summary: This module defines classes and functions for converting a CSV file of points of interest with addresses to a KML file for importing into mapping software.
Home-page: UNKNOWN
License: UNKNOWN
Author: Manny Ochoa
Author-email: dev@manuelochoa.com
Requires-Python: >=3.6,<4.0
Classifier: Programming Language :: Python :: 3
Classifier: Programming Language :: Python :: 3.6
Classifier: Programming Language :: Python :: 3.7
Requires-Dist: faker (>=1.0,<2.0)
Requires-Dist: geocoder (>=1.38,<2.0)
Requires-Dist: pandas (>=0.23.4,<0.24.0)
Requires-Dist: pathlib (>=1.0,<2.0)
Requires-Dist: phonenumbers (>=8.10,<9.0)
Requires-Dist: simplekml (>=1.3,<2.0)
Requires-Dist: usaddress (>=0.5.10,<0.6.0)
Requires-Dist: uszipcode (>=0.2.2,<0.3.0)
